License.txt
README.md
setup.py
HKH_Bot.egg-info/PKG-INFO
HKH_Bot.egg-info/SOURCES.txt
HKH_Bot.egg-info/dependency_links.txt
HKH_Bot.egg-info/entry_points.txt
HKH_Bot.egg-info/namespace_packages.txt
HKH_Bot.egg-info/requires.txt
HKH_Bot.egg-info/top_level.txt
orangecontrib/__init__.py
orangecontrib/hkh_bot/__init__.py
orangecontrib/hkh_bot/widgets/Chatbot.py
orangecontrib/hkh_bot/widgets/DocumentEater.py
orangecontrib/hkh_bot/widgets/EmbeddingsCreation.py
orangecontrib/hkh_bot/widgets/LanguageModel.py
orangecontrib/hkh_bot/widgets/TextPreprocessing.py
orangecontrib/hkh_bot/widgets/__init__.py
orangecontrib/hkh_bot/widgets/icons/Chatbot.svg
orangecontrib/hkh_bot/widgets/icons/DocumentEater.svg
orangecontrib/hkh_bot/widgets/icons/Embeddings.svg
orangecontrib/hkh_bot/widgets/icons/LanguageModel.svg
orangecontrib/hkh_bot/widgets/icons/TextPreprocessing.svg